informer/__init__.py
informer/config.py
informer/informer.py
informer/network.py
informer/utils.py
informer-0.0.6.dist-info/LICENSE
informer-0.0.6.dist-info/METADATA
informer-0.0.6.dist-info/WHEEL
informer-0.0.6.dist-info/top_level.txt
informer-0.0.6.dist-info/RECORD
